easeml/__init__.py
easeml/commands/__init__.py
easeml/commands/action.py
easeml/commands/batch.py
easeml/commands/client.py
easeml/commands/create.py
easeml/commands/download.py
easeml/commands/hookspecs.py
easeml/commands/show.py
easeml/model/__init__.py
easeml/model/common.py
easeml/model/core.py
easeml/model/dataset.py
easeml/model/job.py
easeml/model/module.py
easeml/model/process.py
easeml/model/task.py
easeml/model/type.py
easeml/model/user.py
easeml-0.0.1.dev3.dist-info/LICENCE
easeml-0.0.1.dev3.dist-info/METADATA
easeml-0.0.1.dev3.dist-info/WHEEL
easeml-0.0.1.dev3.dist-info/entry_points.txt
easeml-0.0.1.dev3.dist-info/top_level.txt
easeml-0.0.1.dev3.dist-info/RECORD
