Metadata-Version: 2.1
Name: easeml
Version: 0.0.1.dev3
Summary: Client library used to communicate with the ease.ml service.
Home-page: https://github.com/DS3Lab/easeml
Author: Bojan Karlas, Leonel Aguilar
Author-email: bojan.karlas@gmail.com, leonel.aguilar.m@gmail.com
License: MIT
Platform: UNKNOWN
Classifier: Programming Language :: Python :: 3
Classifier: License :: OSI Approved :: MIT License
Classifier: Operating System :: OS Independent
Requires-Dist: requests (>=2.22.0)
Requires-Dist: pyrfc3339 (>=1.1)
Requires-Dist: tuspy (>=0.2.4)
Requires-Dist: docker (>=4.0.1)
Requires-Dist: pluggy (<1.0,>=0.3)
Requires-Dist: PyYAML (>=5.3.1)
